termprofiles/__init__.py
termprofiles/cli.py
termprofiles/doctor.py
termprofiles/mac.py
termprofiles/util.py
termprofiles/win.py
termprofiles-0.1.3.dist-info/licenses/LICENSE
termprofiles-0.1.3.dist-info/METADATA
termprofiles-0.1.3.dist-info/WHEEL
termprofiles-0.1.3.dist-info/entry_points.txt
termprofiles-0.1.3.dist-info/top_level.txt
termprofiles-0.1.3.dist-info/RECORD
