Metadata-Version: 2.4
Name: termprofiles
Version: 0.1.3
Summary: Per-project terminal profiles for iTerm2 (macOS) and Windows Terminal (Windows), safely via per-file JSON.
Author-email: yaioyaio <yaioyaio@gmail.com>
License-Expression: MIT
Project-URL: Homepage, https://github.com/yaioyaio/termprofiles
Project-URL: Repository, https://github.com/yaioyaio/termprofiles
Project-URL: Documentation, https://github.com/yaioyaio/termprofiles#readme
Project-URL: Bug Tracker, https://github.com/yaioyaio/termprofiles/issues
Project-URL: Release Notes, https://github.com/yaioyaio/termprofiles/releases
Keywords: terminal,iterm2,windows terminal,zsh,profiles,cli,productivity
Classifier: Development Status :: 4 - Beta
Classifier: Environment :: Console
Classifier: Intended Audience :: Developers
Classifier: Intended Audience :: System Administrators
Classifier: Operating System :: MacOS
Classifier: Operating System :: Microsoft :: Windows
Classifier: Programming Language :: Python :: 3
Classifier: Topic :: System :: Shells
Classifier: Topic :: Utilities
Requires-Python: >=3.8
License-File: LICENSE
Dynamic: license-file
